odoo/addons/import_cooperator_energetica/.gitignore
odoo/addons/import_cooperator_energetica/.pre-commit-config.yaml
odoo/addons/import_cooperator_energetica/.pylintrc
odoo/addons/import_cooperator_energetica/NEWS.rst
odoo/addons/import_cooperator_energetica/README.md
odoo/addons/import_cooperator_energetica/__init__.py
odoo/addons/import_cooperator_energetica/__manifest__.py
odoo/addons/import_cooperator_energetica/data/ir_action_server.xml
odoo/addons/import_cooperator_energetica/models/__init__.py
odoo/addons/import_cooperator_energetica/models/import_cooperator.py
odoo/addons/import_cooperator_energetica/models/__pycache__/__init__.cpython-311.pyc
odoo/addons/import_cooperator_energetica/models/__pycache__/import_cooperator.cpython-311.pyc
odoo/addons/import_cooperator_energetica/security/ir.model.access.csv
odoo/addons/import_cooperator_energetica/views/import_cooperator_view.xml
odoo/addons/import_cooperator_energetica/views/menuitems.xml
odoo_addon_import_cooperator_energetica-16.0.4.0.0.dist-info/METADATA
odoo_addon_import_cooperator_energetica-16.0.4.0.0.dist-info/WHEEL
odoo_addon_import_cooperator_energetica-16.0.4.0.0.dist-info/top_level.txt
odoo_addon_import_cooperator_energetica-16.0.4.0.0.dist-info/RECORD
